{
  "dependencies": [
    {
      "source": {
        "git": {
          "remote": "https://github.com/grafana/grafonnet-lib",
          "subdir": "grafonnet"
        }
      },
      "version": "master"
    },
    {
      "source": {
        "git": {
          "remote": "https://github.com/grafana/jsonnet-libs",
          "subdir": "grafana-builder"
        }
      },
      "version": "master"
    },
    {
      "source": {
        "local": {
          "directory": "thanos"
        }
      },
      "version": ".",
      "name": "thanos-mixin"
    }
  ],
  "legacyImports": true
}
