{
  "title": "Interactive Thanos Deployment for Global View and HA of Prometheus Servers",
  "description": "...",
  "details": {
    "steps": [
      {
        "title": "Step 1",
        "text": "step1.md"
      },
      {
        "title": "Step 2",
        "text": "step2.md"
      },
      {
        "title": "Step 3",
        "text": "step3.md"
      }
    ],
    "intro": {
      "text": "intro.md"
    },
    "finish": {
      "text": "finish.md"
    }
  },
  "environment": {
    "uilayout": "editor-terminal"
  },
  "backend": {
    "imageid": "docker"
  }
}